{
    "Eco-Dome Al'dani": {
        "acronym": "EDA"
    },
    "Ara-Kara, City of Echoes": {
        "acronym": "ARAK"
    },
    "The Dawnbreaker": {
        "acronym": "DAWN"
    },
    "Priory of the Sacred Flame": {
        "acronym": "PSF"
    },
    "Operation: Floodgate": {
        "acronym": "FLOOD"
    },
    "Halls of Atonement": {
        "acronym": "HOA"
    },
    "Tazavesh: Streets of Wonder": {
        "acronym": "STRT"
    },
    "Tazavesh: So'leah's Gambit": {
        "acronym": "GMBT"
    }
}
